napari_aisegcell/__init__.py
napari_aisegcell/_sample_data.py
napari_aisegcell/_utils.py
napari_aisegcell/_version.py
napari_aisegcell/_widget_batch_mode.py
napari_aisegcell/_widget_layer_mode.py
napari_aisegcell/napari.yaml
napari_aisegcell/_tests/__init__.py
napari_aisegcell/_tests/test_sample_data.py
napari_aisegcell/_tests/test_utils.py
napari_aisegcell/_tests/test_widget_batch_mode.py
napari_aisegcell/_tests/test_widget_layer_mode.py
napari_aisegcell-0.1.0.dist-info/LICENSE
napari_aisegcell-0.1.0.dist-info/METADATA
napari_aisegcell-0.1.0.dist-info/WHEEL
napari_aisegcell-0.1.0.dist-info/entry_points.txt
napari_aisegcell-0.1.0.dist-info/top_level.txt
napari_aisegcell-0.1.0.dist-info/RECORD
