Metadata-Version: 2.1
Name: napari-aisegcell
Version: 0.1.0
Summary: napari plugin for deep learning-based segmentation of bright field images
Home-page: https://github.com/CSDGroup/napari-aisegcell
Author: Daniel Schirmacher
Author-email: dschirethz@gmail.com
License: BSD-3-Clause
Project-URL: Bug Tracker, https://github.com/CSDGroup/napari-aisegcell/issues
Project-URL: Documentation, https://github.com/CSDGroup/napari-aisegcell#README.md
Project-URL: Source Code, https://github.com/CSDGroup/napari-aisegcell
Project-URL: User Support, https://github.com/CSDGroup/napari-aisegcell/issues
Classifier: Development Status :: 4 - Beta
Classifier: Intended Audience :: Developers
Classifier: License :: OSI Approved :: BSD License
Classifier: Operating System :: OS Independent
Classifier: Programming Language :: Python
Classifier: Programming Language :: Python :: 3
Classifier: Programming Language :: Python :: 3 :: Only
Classifier: Programming Language :: Python :: 3.8
Classifier: Programming Language :: Python :: 3.9
Classifier: Topic :: Scientific/Engineering :: Image Processing
Requires-Python: <3.10,>=3.8
License-File: LICENSE
Requires-Dist: numpy
Requires-Dist: magicgui
Requires-Dist: qtpy
Requires-Dist: pooch
Requires-Dist: imageio <2.28.0
Requires-Dist: scikit-image
Requires-Dist: light-the-torch
Requires-Dist: aisegcell
Provides-Extra: testing
Requires-Dist: tox ; extra == 'testing'
Requires-Dist: pytest ; extra == 'testing'
Requires-Dist: pytest-cov ; extra == 'testing'
Requires-Dist: pytest-qt ; extra == 'testing'
Requires-Dist: napari ; extra == 'testing'
Requires-Dist: pyqt5 ; extra == 'testing'
